usageguard/__init__.py
usageguard/adapter.py
usageguard/api_client.py
usageguard/client.py
usageguard/types.py
usageguard/adapters/__init__.py
usageguard/adapters/google.py
usageguard/adapters/openai.py
usageguard-0.1.0.dist-info/licenses/LICENSE
usageguard-0.1.0.dist-info/METADATA
usageguard-0.1.0.dist-info/WHEEL
usageguard-0.1.0.dist-info/top_level.txt
usageguard-0.1.0.dist-info/RECORD
