Metadata-Version: 2.4
Name: usageguard
Version: 0.1.0
Summary: Real-time cost control for AI and API platforms
Author-email: UsageGuard Team <support@usageguard.ai>
License: MIT
Project-URL: Homepage, https://usage-guard.vercel.app
Project-URL: Documentation, https://usage-guard.vercel.app/docs
Project-URL: Repository, https://github.com/sherlocq61/UsageGuard
Keywords: ai,api,cost-control,openai,anthropic,gemini,budget
Classifier: Development Status :: 4 - Beta
Classifier: Intended Audience :: Developers
Classifier: License :: OSI Approved :: MIT License
Classifier: Programming Language :: Python :: 3
Classifier: Programming Language :: Python :: 3.8
Classifier: Programming Language :: Python :: 3.9
Classifier: Programming Language :: Python :: 3.10
Classifier: Programming Language :: Python :: 3.11
Requires-Python: >=3.8
License-File: LICENSE
Requires-Dist: requests>=2.28.0
Requires-Dist: openai>=1.0.0
Provides-Extra: dev
Requires-Dist: pytest>=7.0.0; extra == "dev"
Requires-Dist: pytest-cov>=4.0.0; extra == "dev"
Requires-Dist: black>=23.0.0; extra == "dev"
Requires-Dist: mypy>=1.0.0; extra == "dev"
Dynamic: license-file
